camphr_embedrank/VERSION.py
camphr_embedrank/__init__.py
camphr_embedrank/embedrank.py
camphr_embedrank-0.1.0.dist-info/WHEEL
camphr_embedrank-0.1.0.dist-info/METADATA
camphr_embedrank-0.1.0.dist-info/RECORD
