Metadata-Version: 2.1
Name: camphr-embedrank
Version: 0.1.0
Summary: 
Home-page: https://github.com/PKSHATechnology-Research/camphr
License: Apache-2.0
Author: tamuhey
Author-email: tamuhey@gmail.com
Requires-Python: >=3.7,<4.0
Classifier: License :: OSI Approved :: Apache Software License
Classifier: Programming Language :: Python :: 3
Classifier: Programming Language :: Python :: 3.7
Classifier: Programming Language :: Python :: 3.8
Classifier: Programming Language :: Python :: 3.9
Requires-Dist: camphr_core (>=0.1.0,<0.2.0)
Requires-Dist: numpy (>=1.20.3,<2.0.0)
Requires-Dist: scikit-learn (>=0.22,<0.25)
Requires-Dist: typing-extensions (>=3.7.4)
Project-URL: Repository, https://github.com/PKSHATechnology-Research/camphr
